surena/__main__.py
surena/cli/commands/__init__.py
surena/cli/commands/docker_host.py
surena/cli/commands/get_docker_host.py
surena/cli/options/__init__.py
surena/cli/options/port.py
surena/cli/options/required_if_option_has_specific_value.py
surena/models/commons/__init__.py
surena/models/commons/countdown.py
surena/models/docker_host/__init__.py
surena/models/docker_host/docker_host.py
surena/models/docker_host/ubuntu.Dockerfile
surena/models/spy_container/WARNING.surena
surena/models/spy_container/__init__.py
surena/models/spy_container/spy_container.py
surena/models/ssh/__init__.py
surena/models/ssh/client.py
surena-0.1.3.dist-info/LICENSE
surena-0.1.3.dist-info/METADATA
surena-0.1.3.dist-info/WHEEL
surena-0.1.3.dist-info/entry_points.txt
surena-0.1.3.dist-info/RECORD
