Metadata-Version: 2.1
Name: surena
Version: 0.1.3
Summary: 
Author: Mohammad Norouzzadegan
Author-email: Norouzzadegan@gmail.com
Requires-Python: >=3.8.10,<4.0.0
Classifier: Programming Language :: Python :: 3
Classifier: Programming Language :: Python :: 3.9
Classifier: Programming Language :: Python :: 3.10
Classifier: Programming Language :: Python :: 3.11
Classifier: Programming Language :: Python :: 3.12
Requires-Dist: click (>=8.1.7,<9.0.0)
Requires-Dist: docker (>=7.0.0,<8.0.0)
Requires-Dist: paramiko (>=3.4.0,<4.0.0)
Requires-Dist: types-paramiko (>=3.4.0.20240205,<4.0.0.0)
Requires-Dist: types-requests (>=2.31.0.20240125,<3.0.0.0)
